pyfiq/__init__.py
pyfiq/backend.py
pyfiq/consumer.py
pyfiq/manager.py
pyfiq/producer.py
pyfiq/registry.py
pyfiq/task.py
pyfiq/workers/__init__.py
pyfiq/workers/asyncio.py
pyfiq/workers/threading.py
pyfiq-0.1.1.dist-info/licenses/LICENSE
pyfiq-0.1.1.dist-info/METADATA
pyfiq-0.1.1.dist-info/WHEEL
pyfiq-0.1.1.dist-info/top_level.txt
pyfiq-0.1.1.dist-info/RECORD
