Metadata-Version: 2.4
Name: pyfiq
Version: 0.1.1
Summary: No drama. Just ordered execution.
Author-email: Robert Wikman <rbw@vault13.org>
Requires-Python: >=3.9
License-File: LICENSE
Requires-Dist: redis>=4.0.0
Provides-Extra: dev
Requires-Dist: pytest; extra == "dev"
Dynamic: license-file
